pymolvis/PyMolVis.py
pymolvis/__all__.py
pymolvis/__init__.py
pymolvis/__version__.py
pymolvis/atom.py
pymolvis/bond.py
pymolvis/bond_critical.py
pymolvis/calc.py
pymolvis/crystal.py
pymolvis/efield.py
pymolvis/molecule.py
pymolvis/orbitals.py
pymolvis/sa_cli.py
pymolvis/surface.py
pymolvis/symm.py
pymolvis/symm_util.py
pymolvis/symmetry.py
pymolvis/write_util.py
pymolvis/ab_initio/__init__.py
pymolvis/ab_initio/ab_init_gui.py
pymolvis/ab_initio/ab_initio_driver.py
pymolvis/ab_initio/ab_initio_orbitals.py
pymolvis/assets/__init__.py
pymolvis-0.3.0.dist-info/licenses/LICENSE
pymolvis-0.3.0.dist-info/METADATA
pymolvis-0.3.0.dist-info/WHEEL
pymolvis-0.3.0.dist-info/entry_points.txt
pymolvis-0.3.0.dist-info/top_level.txt
pymolvis-0.3.0.dist-info/RECORD
